{
  "gorevler": [
    {
      "id": "4dfe4ae9-172d-4f13-9a21-590c0950c7ca",
      "title": "Matematik Türev Çalışması",
      "description": "Türev kurallarını ve uygulamalarını çalış",
      "priority": "medium",
      "category": "genel",
      "color": "#8B5CF6",
      "completed": false,
      "completedAt": null,
      "archived": false,
      "archivedAt": null,
      "deleted": true,
      "deletedAt": "2025-10-31T10:18:16.622Z",
      "dueDate": "2025-10-30",
      "recurrenceType": "none",
      "recurrenceEndDate": null,
      "createdAt": "2025-10-30T17:27:03.212Z"
    },
    {
      "id": "a28064a2-e1da-4769-8c1e-3f5708a745a9",
      "title": "Fizik Denemesi Çöz",
      "description": "Elektrik ve manyetizma denemesi",
      "priority": "medium",
      "category": "genel",
      "color": "#8B5CF6",
      "completed": false,
      "completedAt": null,
      "archived": false,
      "archivedAt": null,
      "deleted": true,
      "deletedAt": "2025-10-31T10:18:16.021Z",
      "dueDate": "2025-10-30",
      "recurrenceType": "none",
      "recurrenceEndDate": null,
      "createdAt": "2025-10-30T17:27:06.875Z"
    },
    {
      "id": "83158003-c7b0-4e89-a165-574087143808",
      "title": "Kimya Formül Tekrarı",
      "description": "Organik kimya formüllerini ezberle",
      "priority": "medium",
      "category": "genel",
      "color": "#8B5CF6",
      "completed": false,
      "completedAt": null,
      "archived": false,
      "archivedAt": null,
      "deleted": true,
      "deletedAt": "2025-10-31T10:18:15.300Z",
      "dueDate": "2025-10-30",
      "recurrenceType": "none",
      "recurrenceEndDate": null,
      "createdAt": "2025-10-30T17:27:10.544Z"
    },
    {
      "id": "3c1f13d4-0ce1-4c4b-8b7a-c841a6484f51",
      "title": "Biyoloji Konu Özeti",
      "description": "Genetik ve kalıtım özeti çıkar",
      "priority": "medium",
      "category": "genel",
      "color": "#8B5CF6",
      "completed": false,
      "completedAt": null,
      "archived": false,
      "archivedAt": null,
      "deleted": true,
      "deletedAt": "2025-10-31T10:18:14.537Z",
      "dueDate": "2025-10-30",
      "recurrenceType": "none",
      "recurrenceEndDate": null,
      "createdAt": "2025-10-30T17:27:14.182Z"
    },
    {
      "id": "fdc571c8-eb27-4e72-bb57-091c9e22f267",
      "title": "Türkçe Paragraf Çalış",
      "description": "Ana fikir bulma teknikleri",
      "priority": "medium",
      "category": "genel",
      "color": "#8B5CF6",
      "completed": false,
      "completedAt": null,
      "archived": false,
      "archivedAt": null,
      "deleted": true,
      "deletedAt": "2025-10-31T10:18:13.417Z",
      "dueDate": "2025-10-30",
      "recurrenceType": "none",
      "recurrenceEndDate": null,
      "createdAt": "2025-10-30T17:27:17.859Z"
    }
  ],
  "ruhHalleri": [],
  "hedefler": [],
  "soruGunlukleri": [],
  "sinavSonuclari": [],
  "sinavKonuNetleri": [],
  "calismaSaatleri": []
}